{"USD/ILS":{"meta":{"symbol":"USD/ILS","interval":"5min","currency_base":"US Dollar","currency_quote":"Israeli Shekel","type":"Physical Currency"},"values":[{"datetime":"2025-02-18 00:30:00","open":"3.55520","high":"3.55560","low":"3.55510","close":"3.55550"}],"status":"ok"},"USD/GBP":{"meta":{"symbol":"USD/GBP","interval":"5min","currency_base":"US Dollar","currency_quote":"British Pound","type":"Physical Currency"},"values":[{"datetime":"2025-02-18 00:30:00","open":"0.79386503","high":"0.79386503","low":"0.79370999","close":"0.79372501"}],"status":"ok"},"USD/EUR":{"meta":{"symbol":"USD/EUR","interval":"5min","currency_base":"US Dollar","currency_quote":"Euro","type":"Physical Currency"},"values":[{"datetime":"2025-02-18 00:30:00","open":"0.95506501","high":"0.95522499","low":"0.95506501","close":"0.95522499"}],"status":"ok"}}
